{
  "object": "card",
  "id": "17558592-2e66-48d3-b38a-3738e5a2a01f",
  "oracle_id": "57296ea3-3c0d-49b7-bc08-0d0d8414e9ad",
  "multiverse_ids": [],
  "tcgplayer_id": 537703,
  "name": "Nightscape Familiar",
  "lang": "en",
  "released_at": "2024-02-05",
  "uri": "https://api.scryfall.com/cards/17558592-2e66-48d3-b38a-3738e5a2a01f",
  "scryfall_uri": "https://scryfall.com/card/sld/1546%E2%98%85/nightscape-familiar?utm_source=api",
  "layout": "normal",
  "highres_image": true,
  "image_status": "highres_scan",
  "image_uris": {
    "small": "https://cards.scryfall.io/small/front/1/7/17558592-2e66-48d3-b38a-3738e5a2a01f.jpg?1707868840",
    "normal": "https://cards.scryfall.io/normal/front/1/7/17558592-2e66-48d3-b38a-3738e5a2a01f.jpg?1707868840",
    "large": "https://cards.scryfall.io/large/front/1/7/17558592-2e66-48d3-b38a-3738e5a2a01f.jpg?1707868840",
    "png": "https://cards.scryfall.io/png/front/1/7/17558592-2e66-48d3-b38a-3738e5a2a01f.png?1707868840",
    "art_crop": "https://cards.scryfall.io/art_crop/front/1/7/17558592-2e66-48d3-b38a-3738e5a2a01f.jpg?1707868840",
    "border_crop": "https://cards.scryfall.io/border_crop/front/1/7/17558592-2e66-48d3-b38a-3738e5a2a01f.jpg?1707868840"
  },
  "mana_cost": "{1}{B}",
  "cmc": 2,
  "type_line": "Creature — Zombie",
  "oracle_text": "Blue spells and red spells you cast cost {1} less to cast.\n{1}{B}: Regenerate this creature.",
  "power": "1",
  "toughness": "1",
  "colors": [
    "B"
  ],
  "color_identity": [
    "B"
  ],
  "keywords": [],
  "legalities": {
    "standard": "not_legal",
    "future": "not_legal",
    "historic": "not_legal",
    "timeless": "not_legal",
    "gladiator": "not_legal",
    "pioneer": "not_legal",
    "modern": "not_legal",
    "legacy": "legal",
    "pauper": "legal",
    "vintage": "legal",
    "penny": "legal",
    "commander": "legal",
    "oathbreaker": "legal",
    "standardbrawl": "not_legal",
    "brawl": "not_legal",
    "alchemy": "not_legal",
    "paupercommander": "legal",
    "duel": "legal",
    "oldschool": "not_legal",
    "premodern": "legal",
    "predh": "legal"
  },
  "games": [
    "paper"
  ],
  "reserved": false,
  "game_changer": false,
  "foil": true,
  "nonfoil": false,
  "finishes": [
    "foil"
  ],
  "oversized": false,
  "promo": false,
  "reprint": true,
  "variation": false,
  "set_id": "4d92a8a7-ccb0-437d-abdc-9d70fc5ed672",
  "set": "sld",
  "set_name": "Secret Lair Drop",
  "set_type": "box",
  "set_uri": "https://api.scryfall.com/sets/4d92a8a7-ccb0-437d-abdc-9d70fc5ed672",
  "set_search_uri": "https://api.scryfall.com/cards/search?order=set&q=e%3Asld&unique=prints",
  "scryfall_set_uri": "https://scryfall.com/sets/sld?utm_source=api",
  "rulings_uri": "https://api.scryfall.com/cards/17558592-2e66-48d3-b38a-3738e5a2a01f/rulings",
  "prints_search_uri": "https://api.scryfall.com/cards/search?order=released&q=oracleid%3A57296ea3-3c0d-49b7-bc08-0d0d8414e9ad&unique=prints",
  "collector_number": "1546★",
  "digital": false,
  "rarity": "rare",
  "flavor_text": "Nightscape masters prize one trait above all others: undying loyalty.",
  "card_back_id": "0aeebaf5-8c7d-4636-9e82-8c27447861f7",
  "artist": "Graham Yarrington",
  "artist_ids": [
    "22e64ba1-8baf-4c6e-900c-b01485ab4c9d"
  ],
  "illustration_id": "21e38a4b-5aa8-4725-851a-51629e29e406",
  "border_color": "borderless",
  "frame": "2015",
  "security_stamp": "oval",
  "full_art": true,
  "textless": false,
  "booster": false,
  "story_spotlight": false,
  "promo_types": [
    "rainbowfoil"
  ],
  "edhrec_rank": 1267,
  "penny_rank": 2236,
  "prices": {
    "usd": null,
    "usd_foil": "9.47",
    "usd_etched": null,
    "eur": null,
    "eur_foil": null,
    "tix": null
  },
  "related_uris": {
    "tcgplayer_infinite_articles": "https://partner.tcgplayer.com/c/4931599/1830156/21018?subId1=api&trafcat=tcgplayer.com%2Fsearch%2Farticles&u=https%3A%2F%2Fwww.tcgplayer.com%2Fsearch%2Farticles%3FproductLineName%3Dmagic%26q%3DNightscape%2BFamiliar",
    "tcgplayer_infinite_decks": "https://partner.tcgplayer.com/c/4931599/1830156/21018?subId1=api&trafcat=tcgplayer.com%2Fsearch%2Fdecks&u=https%3A%2F%2Fwww.tcgplayer.com%2Fsearch%2Fdecks%3FproductLineName%3Dmagic%26q%3DNightscape%2BFamiliar",
    "edhrec": "https://edhrec.com/route/?cc=Nightscape+Familiar"
  },
  "purchase_uris": {
    "tcgplayer": "https://partner.tcgplayer.com/c/4931599/1830156/21018?subId1=api&u=https%3A%2F%2Fwww.tcgplayer.com%2Fproduct%2F537703%3Fpage%3D1",
    "cardmarket": "https://www.cardmarket.com/en/Magic/Products/Search?referrer=scryfall&searchString=Nightscape+Familiar&utm_campaign=card_prices&utm_medium=text&utm_source=scryfall",
    "cardhoarder": "https://www.cardhoarder.com/cards?affiliate_id=scryfall&data%5Bsearch%5D=Nightscape+Familiar&ref=card-profile&utm_campaign=affiliate&utm_medium=card&utm_source=scryfall"
  }
}