{
  "object": "card",
  "id": "2ec07b33-5d11-4bab-a01a-f6531e0b8a2a",
  "oracle_id": "204f9afe-c20b-4933-b5cd-aa572784762a",
  "multiverse_ids": [],
  "tcgplayer_id": 15239,
  "cardmarket_id": 16448,
  "name": "Overrun",
  "lang": "en",
  "released_at": "2007-07-13",
  "uri": "https://api.scryfall.com/cards/2ec07b33-5d11-4bab-a01a-f6531e0b8a2a",
  "scryfall_uri": "https://scryfall.com/card/10e/284%E2%98%85/overrun?utm_source=api",
  "layout": "normal",
  "highres_image": true,
  "image_status": "highres_scan",
  "image_uris": {
    "small": "https://cards.scryfall.io/small/front/2/e/2ec07b33-5d11-4bab-a01a-f6531e0b8a2a.jpg?1562545613",
    "normal": "https://cards.scryfall.io/normal/front/2/e/2ec07b33-5d11-4bab-a01a-f6531e0b8a2a.jpg?1562545613",
    "large": "https://cards.scryfall.io/large/front/2/e/2ec07b33-5d11-4bab-a01a-f6531e0b8a2a.jpg?1562545613",
    "png": "https://cards.scryfall.io/png/front/2/e/2ec07b33-5d11-4bab-a01a-f6531e0b8a2a.png?1562545613",
    "art_crop": "https://cards.scryfall.io/art_crop/front/2/e/2ec07b33-5d11-4bab-a01a-f6531e0b8a2a.jpg?1562545613",
    "border_crop": "https://cards.scryfall.io/border_crop/front/2/e/2ec07b33-5d11-4bab-a01a-f6531e0b8a2a.jpg?1562545613"
  },
  "mana_cost": "{2}{G}{G}{G}",
  "cmc": 5,
  "type_line": "Sorcery",
  "oracle_text": "Creatures you control get +3/+3 and gain trample until end of turn. (Each of those creatures can deal excess combat damage to the player or planeswalker it's attacking.)",
  "colors": [
    "G"
  ],
  "color_identity": [
    "G"
  ],
  "keywords": [],
  "legalities": {
    "standard": "legal",
    "future": "legal",
    "historic": "legal",
    "timeless": "legal",
    "gladiator": "legal",
    "pioneer": "legal",
    "modern": "legal",
    "legacy": "legal",
    "pauper": "not_legal",
    "vintage": "legal",
    "penny": "not_legal",
    "commander": "legal",
    "oathbreaker": "legal",
    "standardbrawl": "legal",
    "brawl": "legal",
    "alchemy": "legal",
    "paupercommander": "not_legal",
    "duel": "legal",
    "oldschool": "not_legal",
    "premodern": "legal",
    "predh": "legal"
  },
  "games": [
    "paper",
    "mtgo"
  ],
  "reserved": false,
  "game_changer": false,
  "foil": true,
  "nonfoil": false,
  "finishes": [
    "foil"
  ],
  "oversized": false,
  "promo": false,
  "reprint": true,
  "variation": false,
  "set_id": "a66a6124-0d81-488d-b080-91f5ba7fbad0",
  "set": "10e",
  "set_name": "Tenth Edition",
  "set_type": "core",
  "set_uri": "https://api.scryfall.com/sets/a66a6124-0d81-488d-b080-91f5ba7fbad0",
  "set_search_uri": "https://api.scryfall.com/cards/search?order=set&q=e%3A10e&unique=prints",
  "scryfall_set_uri": "https://scryfall.com/sets/10e?utm_source=api",
  "rulings_uri": "https://api.scryfall.com/cards/2ec07b33-5d11-4bab-a01a-f6531e0b8a2a/rulings",
  "prints_search_uri": "https://api.scryfall.com/cards/search?order=released&q=oracleid%3A204f9afe-c20b-4933-b5cd-aa572784762a&unique=prints",
  "collector_number": "284★",
  "digital": false,
  "rarity": "uncommon",
  "flavor_text": "Nature doesn't walk.",
  "card_back_id": "0aeebaf5-8c7d-4636-9e82-8c27447861f7",
  "artist": "Carl Critchlow",
  "artist_ids": [
    "17948f16-611a-44b8-8d10-9895a0bdfff1"
  ],
  "illustration_id": "548a75f8-7ac3-4045-a729-7018fcc4048a",
  "border_color": "black",
  "frame": "2003",
  "full_art": false,
  "textless": false,
  "booster": true,
  "story_spotlight": false,
  "edhrec_rank": 1677,
  "penny_rank": 2815,
  "prices": {
    "usd": null,
    "usd_foil": "1.20",
    "usd_etched": null,
    "eur": null,
    "eur_foil": "1.45",
    "tix": null
  },
  "related_uris": {
    "tcgplayer_infinite_articles": "https://partner.tcgplayer.com/c/4931599/1830156/21018?subId1=api&trafcat=tcgplayer.com%2Fsearch%2Farticles&u=https%3A%2F%2Fwww.tcgplayer.com%2Fsearch%2Farticles%3FproductLineName%3Dmagic%26q%3DOverrun",
    "tcgplayer_infinite_decks": "https://partner.tcgplayer.com/c/4931599/1830156/21018?subId1=api&trafcat=tcgplayer.com%2Fsearch%2Fdecks&u=https%3A%2F%2Fwww.tcgplayer.com%2Fsearch%2Fdecks%3FproductLineName%3Dmagic%26q%3DOverrun",
    "edhrec": "https://edhrec.com/route/?cc=Overrun"
  },
  "purchase_uris": {
    "tcgplayer": "https://partner.tcgplayer.com/c/4931599/1830156/21018?subId1=api&u=https%3A%2F%2Fwww.tcgplayer.com%2Fproduct%2F15239%3Fpage%3D1",
    "cardmarket": "https://www.cardmarket.com/en/Magic/Products?idProduct=16448&referrer=scryfall&utm_campaign=card_prices&utm_medium=text&utm_source=scryfall",
    "cardhoarder": "https://www.cardhoarder.com/cards?affiliate_id=scryfall&data%5Bsearch%5D=Overrun&ref=card-profile&utm_campaign=affiliate&utm_medium=card&utm_source=scryfall"
  }
}