{
  "object": "card",
  "id": "457097be-6737-4873-a6fd-28ae18cc722a",
  "oracle_id": "7a2484a9-04fd-41a0-8224-610c1c07ed10",
  "multiverse_ids": [],
  "tcgplayer_id": 625942,
  "cardmarket_id": 820174,
  "name": "Blasphemous Act",
  "lang": "en",
  "released_at": "2025-04-01",
  "uri": "https://api.scryfall.com/cards/457097be-6737-4873-a6fd-28ae18cc722a",
  "scryfall_uri": "https://scryfall.com/card/sld/1756/blasphemous-act?utm_source=api",
  "layout": "normal",
  "highres_image": true,
  "image_status": "highres_scan",
  "image_uris": {
    "small": "https://cards.scryfall.io/small/front/4/5/457097be-6737-4873-a6fd-28ae18cc722a.jpg?1743765766",
    "normal": "https://cards.scryfall.io/normal/front/4/5/457097be-6737-4873-a6fd-28ae18cc722a.jpg?1743765766",
    "large": "https://cards.scryfall.io/large/front/4/5/457097be-6737-4873-a6fd-28ae18cc722a.jpg?1743765766",
    "png": "https://cards.scryfall.io/png/front/4/5/457097be-6737-4873-a6fd-28ae18cc722a.png?1743765766",
    "art_crop": "https://cards.scryfall.io/art_crop/front/4/5/457097be-6737-4873-a6fd-28ae18cc722a.jpg?1743765766",
    "border_crop": "https://cards.scryfall.io/border_crop/front/4/5/457097be-6737-4873-a6fd-28ae18cc722a.jpg?1743765766"
  },
  "mana_cost": "{8}{R}",
  "cmc": 9,
  "type_line": "Sorcery",
  "oracle_text": "This spell costs {1} less to cast for each creature on the battlefield.\nBlasphemous Act deals 13 damage to each creature.",
  "colors": [
    "R"
  ],
  "color_identity": [
    "R"
  ],
  "keywords": [],
  "legalities": {
    "standard": "not_legal",
    "future": "not_legal",
    "historic": "not_legal",
    "timeless": "not_legal",
    "gladiator": "not_legal",
    "pioneer": "not_legal",
    "modern": "legal",
    "legacy": "legal",
    "pauper": "not_legal",
    "vintage": "legal",
    "penny": "legal",
    "commander": "legal",
    "oathbreaker": "legal",
    "standardbrawl": "not_legal",
    "brawl": "not_legal",
    "alchemy": "not_legal",
    "paupercommander": "not_legal",
    "duel": "legal",
    "oldschool": "not_legal",
    "premodern": "not_legal",
    "predh": "not_legal"
  },
  "games": [
    "paper"
  ],
  "reserved": false,
  "game_changer": false,
  "foil": true,
  "nonfoil": true,
  "finishes": [
    "nonfoil",
    "foil"
  ],
  "oversized": false,
  "promo": false,
  "reprint": true,
  "variation": false,
  "set_id": "4d92a8a7-ccb0-437d-abdc-9d70fc5ed672",
  "set": "sld",
  "set_name": "Secret Lair Drop",
  "set_type": "box",
  "set_uri": "https://api.scryfall.com/sets/4d92a8a7-ccb0-437d-abdc-9d70fc5ed672",
  "set_search_uri": "https://api.scryfall.com/cards/search?order=set&q=e%3Asld&unique=prints",
  "scryfall_set_uri": "https://scryfall.com/sets/sld?utm_source=api",
  "rulings_uri": "https://api.scryfall.com/cards/457097be-6737-4873-a6fd-28ae18cc722a/rulings",
  "prints_search_uri": "https://api.scryfall.com/cards/search?order=released&q=oracleid%3A7a2484a9-04fd-41a0-8224-610c1c07ed10&unique=prints",
  "collector_number": "1756",
  "digital": false,
  "rarity": "rare",
  "flavor_text": "\"You might be wondering why I've killed the Marvel Universe yet again, but the real question is: How am I breathing on the moon?\"",
  "card_back_id": "0aeebaf5-8c7d-4636-9e82-8c27447861f7",
  "artist": "Tomasz Zarucki",
  "artist_ids": [
    "3363f68a-6905-44ce-957a-d27a276132d3"
  ],
  "illustration_id": "164774ef-e6e0-4647-8a67-54ed0060d63f",
  "border_color": "borderless",
  "frame": "2015",
  "frame_effects": [
    "inverted"
  ],
  "security_stamp": "triangle",
  "full_art": true,
  "textless": false,
  "booster": false,
  "story_spotlight": false,
  "edhrec_rank": 25,
  "penny_rank": 2773,
  "prices": {
    "usd": "2.95",
    "usd_foil": null,
    "usd_etched": null,
    "eur": "3.49",
    "eur_foil": "4.47",
    "tix": null
  },
  "related_uris": {
    "tcgplayer_infinite_articles": "https://partner.tcgplayer.com/c/4931599/1830156/21018?subId1=api&trafcat=tcgplayer.com%2Fsearch%2Farticles&u=https%3A%2F%2Fwww.tcgplayer.com%2Fsearch%2Farticles%3FproductLineName%3Dmagic%26q%3DBlasphemous%2BAct",
    "tcgplayer_infinite_decks": "https://partner.tcgplayer.com/c/4931599/1830156/21018?subId1=api&trafcat=tcgplayer.com%2Fsearch%2Fdecks&u=https%3A%2F%2Fwww.tcgplayer.com%2Fsearch%2Fdecks%3FproductLineName%3Dmagic%26q%3DBlasphemous%2BAct",
    "edhrec": "https://edhrec.com/route/?cc=Blasphemous+Act"
  },
  "purchase_uris": {
    "tcgplayer": "https://partner.tcgplayer.com/c/4931599/1830156/21018?subId1=api&u=https%3A%2F%2Fwww.tcgplayer.com%2Fproduct%2F625942%3Fpage%3D1",
    "cardmarket": "https://www.cardmarket.com/en/Magic/Products?idProduct=820174&referrer=scryfall&utm_campaign=card_prices&utm_medium=text&utm_source=scryfall",
    "cardhoarder": "https://www.cardhoarder.com/cards?affiliate_id=scryfall&data%5Bsearch%5D=Blasphemous+Act&ref=card-profile&utm_campaign=affiliate&utm_medium=card&utm_source=scryfall"
  }
}