{
  "object": "card",
  "id": "65f9f9ff-5a28-497a-9126-24c0ae4c33a6",
  "oracle_id": "14cefb15-d833-4c70-80c9-f2d34b6c846b",
  "multiverse_ids": [],
  "tcgplayer_id": 217240,
  "cardmarket_id": 476649,
  "name": "Runed Halo",
  "lang": "en",
  "released_at": "2020-07-03",
  "uri": "https://api.scryfall.com/cards/65f9f9ff-5a28-497a-9126-24c0ae4c33a6",
  "scryfall_uri": "https://scryfall.com/card/pm21/32p/runed-halo?utm_source=api",
  "layout": "normal",
  "highres_image": true,
  "image_status": "highres_scan",
  "image_uris": {
    "small": "https://cards.scryfall.io/small/front/6/5/65f9f9ff-5a28-497a-9126-24c0ae4c33a6.jpg?1596312030",
    "normal": "https://cards.scryfall.io/normal/front/6/5/65f9f9ff-5a28-497a-9126-24c0ae4c33a6.jpg?1596312030",
    "large": "https://cards.scryfall.io/large/front/6/5/65f9f9ff-5a28-497a-9126-24c0ae4c33a6.jpg?1596312030",
    "png": "https://cards.scryfall.io/png/front/6/5/65f9f9ff-5a28-497a-9126-24c0ae4c33a6.png?1596312030",
    "art_crop": "https://cards.scryfall.io/art_crop/front/6/5/65f9f9ff-5a28-497a-9126-24c0ae4c33a6.jpg?1596312030",
    "border_crop": "https://cards.scryfall.io/border_crop/front/6/5/65f9f9ff-5a28-497a-9126-24c0ae4c33a6.jpg?1596312030"
  },
  "mana_cost": "{W}{W}",
  "cmc": 2,
  "type_line": "Enchantment",
  "oracle_text": "As this enchantment enters, choose a card name.\nYou have protection from the chosen card name. (You can't be targeted, dealt damage, or enchanted by anything with that name.)",
  "colors": [
    "W"
  ],
  "color_identity": [
    "W"
  ],
  "keywords": [],
  "legalities": {
    "standard": "not_legal",
    "future": "not_legal",
    "historic": "legal",
    "timeless": "legal",
    "gladiator": "legal",
    "pioneer": "legal",
    "modern": "legal",
    "legacy": "legal",
    "pauper": "not_legal",
    "vintage": "legal",
    "penny": "legal",
    "commander": "legal",
    "oathbreaker": "legal",
    "standardbrawl": "not_legal",
    "brawl": "banned",
    "alchemy": "not_legal",
    "paupercommander": "not_legal",
    "duel": "legal",
    "oldschool": "not_legal",
    "premodern": "not_legal",
    "predh": "legal"
  },
  "games": [
    "paper"
  ],
  "reserved": false,
  "game_changer": false,
  "foil": true,
  "nonfoil": true,
  "finishes": [
    "nonfoil",
    "foil"
  ],
  "oversized": false,
  "promo": true,
  "reprint": true,
  "variation": false,
  "set_id": "d4474b31-acac-4d3b-9baa-b596f829070b",
  "set": "pm21",
  "set_name": "Core Set 2021 Promos",
  "set_type": "promo",
  "set_uri": "https://api.scryfall.com/sets/d4474b31-acac-4d3b-9baa-b596f829070b",
  "set_search_uri": "https://api.scryfall.com/cards/search?order=set&q=e%3Apm21&unique=prints",
  "scryfall_set_uri": "https://scryfall.com/sets/pm21?utm_source=api",
  "rulings_uri": "https://api.scryfall.com/cards/65f9f9ff-5a28-497a-9126-24c0ae4c33a6/rulings",
  "prints_search_uri": "https://api.scryfall.com/cards/search?order=released&q=oracleid%3A14cefb15-d833-4c70-80c9-f2d34b6c846b&unique=prints",
  "collector_number": "32p",
  "digital": false,
  "rarity": "rare",
  "card_back_id": "0aeebaf5-8c7d-4636-9e82-8c27447861f7",
  "artist": "Steve Prescott",
  "artist_ids": [
    "a1139fb8-41f5-4a9e-9a74-f662e1a23b35"
  ],
  "illustration_id": "806cf5c9-daa5-4c1e-9ee3-c33de7037aa8",
  "border_color": "black",
  "frame": "2015",
  "security_stamp": "oval",
  "full_art": false,
  "textless": false,
  "booster": false,
  "story_spotlight": false,
  "promo_types": [
    "stamped",
    "promopack"
  ],
  "edhrec_rank": 16965,
  "penny_rank": 635,
  "prices": {
    "usd": "0.46",
    "usd_foil": "0.24",
    "usd_etched": null,
    "eur": "0.28",
    "eur_foil": "0.45",
    "tix": null
  },
  "related_uris": {
    "tcgplayer_infinite_articles": "https://partner.tcgplayer.com/c/4931599/1830156/21018?subId1=api&trafcat=tcgplayer.com%2Fsearch%2Farticles&u=https%3A%2F%2Fwww.tcgplayer.com%2Fsearch%2Farticles%3FproductLineName%3Dmagic%26q%3DRuned%2BHalo",
    "tcgplayer_infinite_decks": "https://partner.tcgplayer.com/c/4931599/1830156/21018?subId1=api&trafcat=tcgplayer.com%2Fsearch%2Fdecks&u=https%3A%2F%2Fwww.tcgplayer.com%2Fsearch%2Fdecks%3FproductLineName%3Dmagic%26q%3DRuned%2BHalo",
    "edhrec": "https://edhrec.com/route/?cc=Runed+Halo"
  },
  "purchase_uris": {
    "tcgplayer": "https://partner.tcgplayer.com/c/4931599/1830156/21018?subId1=api&u=https%3A%2F%2Fwww.tcgplayer.com%2Fproduct%2F217240%3Fpage%3D1",
    "cardmarket": "https://www.cardmarket.com/en/Magic/Products?idProduct=476649&referrer=scryfall&utm_campaign=card_prices&utm_medium=text&utm_source=scryfall",
    "cardhoarder": "https://www.cardhoarder.com/cards?affiliate_id=scryfall&data%5Bsearch%5D=Runed+Halo&ref=card-profile&utm_campaign=affiliate&utm_medium=card&utm_source=scryfall"
  }
}