{
  "object": "card",
  "id": "88c75247-5e6c-4d4b-be1e-032f76a7c167",
  "oracle_id": "b2187f45-80ae-4ac4-9f83-5eb7a00978e2",
  "multiverse_ids": [],
  "tcgplayer_id": 199932,
  "cardmarket_id": 403564,
  "name": "Sorcerous Spyglass",
  "lang": "en",
  "released_at": "2019-10-04",
  "uri": "https://api.scryfall.com/cards/88c75247-5e6c-4d4b-be1e-032f76a7c167",
  "scryfall_uri": "https://scryfall.com/card/peld/233s/sorcerous-spyglass?utm_source=api",
  "layout": "normal",
  "highres_image": true,
  "image_status": "highres_scan",
  "image_uris": {
    "small": "https://cards.scryfall.io/small/front/8/8/88c75247-5e6c-4d4b-be1e-032f76a7c167.jpg?1571850828",
    "normal": "https://cards.scryfall.io/normal/front/8/8/88c75247-5e6c-4d4b-be1e-032f76a7c167.jpg?1571850828",
    "large": "https://cards.scryfall.io/large/front/8/8/88c75247-5e6c-4d4b-be1e-032f76a7c167.jpg?1571850828",
    "png": "https://cards.scryfall.io/png/front/8/8/88c75247-5e6c-4d4b-be1e-032f76a7c167.png?1571850828",
    "art_crop": "https://cards.scryfall.io/art_crop/front/8/8/88c75247-5e6c-4d4b-be1e-032f76a7c167.jpg?1571850828",
    "border_crop": "https://cards.scryfall.io/border_crop/front/8/8/88c75247-5e6c-4d4b-be1e-032f76a7c167.jpg?1571850828"
  },
  "mana_cost": "{2}",
  "cmc": 2,
  "type_line": "Artifact",
  "oracle_text": "As this artifact enters, look at an opponent's hand, then choose any card name.\nActivated abilities of sources with the chosen name can't be activated unless they're mana abilities.",
  "colors": [],
  "color_identity": [],
  "keywords": [],
  "legalities": {
    "standard": "legal",
    "future": "legal",
    "historic": "legal",
    "timeless": "legal",
    "gladiator": "legal",
    "pioneer": "legal",
    "modern": "legal",
    "legacy": "legal",
    "pauper": "not_legal",
    "vintage": "legal",
    "penny": "legal",
    "commander": "legal",
    "oathbreaker": "legal",
    "standardbrawl": "legal",
    "brawl": "banned",
    "alchemy": "legal",
    "paupercommander": "not_legal",
    "duel": "legal",
    "oldschool": "not_legal",
    "premodern": "not_legal",
    "predh": "not_legal"
  },
  "games": [
    "paper"
  ],
  "reserved": false,
  "game_changer": false,
  "foil": true,
  "nonfoil": false,
  "finishes": [
    "foil"
  ],
  "oversized": false,
  "promo": true,
  "reprint": true,
  "variation": false,
  "set_id": "5f593578-5079-4988-8e88-a3df186bdc2b",
  "set": "peld",
  "set_name": "Throne of Eldraine Promos",
  "set_type": "promo",
  "set_uri": "https://api.scryfall.com/sets/5f593578-5079-4988-8e88-a3df186bdc2b",
  "set_search_uri": "https://api.scryfall.com/cards/search?order=set&q=e%3Apeld&unique=prints",
  "scryfall_set_uri": "https://scryfall.com/sets/peld?utm_source=api",
  "rulings_uri": "https://api.scryfall.com/cards/88c75247-5e6c-4d4b-be1e-032f76a7c167/rulings",
  "prints_search_uri": "https://api.scryfall.com/cards/search?order=released&q=oracleid%3Ab2187f45-80ae-4ac4-9f83-5eb7a00978e2&unique=prints",
  "collector_number": "233s",
  "digital": false,
  "rarity": "rare",
  "card_back_id": "0aeebaf5-8c7d-4636-9e82-8c27447861f7",
  "artist": "Aaron Miller",
  "artist_ids": [
    "fc021f3d-773a-4706-bbe7-f602324f511f"
  ],
  "illustration_id": "1a43f27c-119e-45d8-a36f-074ca00d5986",
  "border_color": "black",
  "frame": "2015",
  "security_stamp": "oval",
  "full_art": false,
  "textless": false,
  "booster": false,
  "story_spotlight": false,
  "promo_types": [
    "prerelease",
    "datestamped"
  ],
  "edhrec_rank": 13929,
  "penny_rank": 705,
  "prices": {
    "usd": null,
    "usd_foil": "0.61",
    "usd_etched": null,
    "eur": null,
    "eur_foil": "0.79",
    "tix": null
  },
  "related_uris": {
    "tcgplayer_infinite_articles": "https://partner.tcgplayer.com/c/4931599/1830156/21018?subId1=api&trafcat=tcgplayer.com%2Fsearch%2Farticles&u=https%3A%2F%2Fwww.tcgplayer.com%2Fsearch%2Farticles%3FproductLineName%3Dmagic%26q%3DSorcerous%2BSpyglass",
    "tcgplayer_infinite_decks": "https://partner.tcgplayer.com/c/4931599/1830156/21018?subId1=api&trafcat=tcgplayer.com%2Fsearch%2Fdecks&u=https%3A%2F%2Fwww.tcgplayer.com%2Fsearch%2Fdecks%3FproductLineName%3Dmagic%26q%3DSorcerous%2BSpyglass",
    "edhrec": "https://edhrec.com/route/?cc=Sorcerous+Spyglass"
  },
  "purchase_uris": {
    "tcgplayer": "https://partner.tcgplayer.com/c/4931599/1830156/21018?subId1=api&u=https%3A%2F%2Fwww.tcgplayer.com%2Fproduct%2F199932%3Fpage%3D1",
    "cardmarket": "https://www.cardmarket.com/en/Magic/Products?idProduct=403564&referrer=scryfall&utm_campaign=card_prices&utm_medium=text&utm_source=scryfall",
    "cardhoarder": "https://www.cardhoarder.com/cards?affiliate_id=scryfall&data%5Bsearch%5D=Sorcerous+Spyglass&ref=card-profile&utm_campaign=affiliate&utm_medium=card&utm_source=scryfall"
  }
}