{
  "object": "card",
  "id": "bf0cbe51-94a3-455e-8224-2fcbbaa041ab",
  "oracle_id": "a4441c7d-e22a-4e19-8365-34d52da9fe86",
  "multiverse_ids": [],
  "tcgplayer_id": 210407,
  "cardmarket_id": 443153,
  "name": "Gilder Bairn",
  "lang": "en",
  "released_at": "2020-03-13",
  "uri": "https://api.scryfall.com/cards/bf0cbe51-94a3-455e-8224-2fcbbaa041ab",
  "scryfall_uri": "https://scryfall.com/card/plst/EVE-152/gilder-bairn?utm_source=api",
  "layout": "normal",
  "highres_image": true,
  "image_status": "highres_scan",
  "image_uris": {
    "small": "https://cards.scryfall.io/small/front/b/f/bf0cbe51-94a3-455e-8224-2fcbbaa041ab.jpg?1583453982",
    "normal": "https://cards.scryfall.io/normal/front/b/f/bf0cbe51-94a3-455e-8224-2fcbbaa041ab.jpg?1583453982",
    "large": "https://cards.scryfall.io/large/front/b/f/bf0cbe51-94a3-455e-8224-2fcbbaa041ab.jpg?1583453982",
    "png": "https://cards.scryfall.io/png/front/b/f/bf0cbe51-94a3-455e-8224-2fcbbaa041ab.png?1583453982",
    "art_crop": "https://cards.scryfall.io/art_crop/front/b/f/bf0cbe51-94a3-455e-8224-2fcbbaa041ab.jpg?1583453982",
    "border_crop": "https://cards.scryfall.io/border_crop/front/b/f/bf0cbe51-94a3-455e-8224-2fcbbaa041ab.jpg?1583453982"
  },
  "mana_cost": "{1}{G/U}{G/U}",
  "cmc": 3,
  "type_line": "Creature — Ouphe",
  "oracle_text": "{2}{G/U}, {Q}: Double the number of each kind of counter on target permanent. ({Q} is the untap symbol.)",
  "power": "1",
  "toughness": "3",
  "colors": [
    "G",
    "U"
  ],
  "color_identity": [
    "G",
    "U"
  ],
  "keywords": [],
  "legalities": {
    "standard": "not_legal",
    "future": "not_legal",
    "historic": "not_legal",
    "timeless": "not_legal",
    "gladiator": "not_legal",
    "pioneer": "not_legal",
    "modern": "legal",
    "legacy": "legal",
    "pauper": "not_legal",
    "vintage": "legal",
    "penny": "not_legal",
    "commander": "legal",
    "oathbreaker": "legal",
    "standardbrawl": "not_legal",
    "brawl": "not_legal",
    "alchemy": "not_legal",
    "paupercommander": "not_legal",
    "duel": "legal",
    "oldschool": "not_legal",
    "premodern": "not_legal",
    "predh": "legal"
  },
  "games": [
    "paper"
  ],
  "reserved": false,
  "game_changer": false,
  "foil": true,
  "nonfoil": false,
  "finishes": [
    "foil"
  ],
  "oversized": false,
  "promo": false,
  "reprint": true,
  "variation": false,
  "set_id": "67e47ba2-b019-4181-9005-fe9fc021de44",
  "set": "plst",
  "set_name": "The List",
  "set_type": "masters",
  "set_uri": "https://api.scryfall.com/sets/67e47ba2-b019-4181-9005-fe9fc021de44",
  "set_search_uri": "https://api.scryfall.com/cards/search?order=set&q=e%3Aplst&unique=prints",
  "scryfall_set_uri": "https://scryfall.com/sets/plst?utm_source=api",
  "rulings_uri": "https://api.scryfall.com/cards/bf0cbe51-94a3-455e-8224-2fcbbaa041ab/rulings",
  "prints_search_uri": "https://api.scryfall.com/cards/search?order=released&q=oracleid%3Aa4441c7d-e22a-4e19-8365-34d52da9fe86&unique=prints",
  "collector_number": "EVE-152",
  "digital": false,
  "rarity": "uncommon",
  "flavor_text": "Do the glowing trinkets show it the way home, or do they set a twisted path for someone else to follow?",
  "card_back_id": "0aeebaf5-8c7d-4636-9e82-8c27447861f7",
  "artist": "Nils Hamm",
  "artist_ids": [
    "c540d1fc-1500-457f-93cf-d6069ee66546"
  ],
  "illustration_id": "cb263396-1ec7-4655-bbb4-75ebe1511a53",
  "border_color": "black",
  "frame": "2003",
  "full_art": false,
  "textless": false,
  "booster": false,
  "story_spotlight": false,
  "edhrec_rank": 14750,
  "penny_rank": 14630,
  "prices": {
    "usd": null,
    "usd_foil": "1.00",
    "usd_etched": null,
    "eur": null,
    "eur_foil": "0.32",
    "tix": null
  },
  "related_uris": {
    "tcgplayer_infinite_articles": "https://partner.tcgplayer.com/c/4931599/1830156/21018?subId1=api&trafcat=tcgplayer.com%2Fsearch%2Farticles&u=https%3A%2F%2Fwww.tcgplayer.com%2Fsearch%2Farticles%3FproductLineName%3Dmagic%26q%3DGilder%2BBairn",
    "tcgplayer_infinite_decks": "https://partner.tcgplayer.com/c/4931599/1830156/21018?subId1=api&trafcat=tcgplayer.com%2Fsearch%2Fdecks&u=https%3A%2F%2Fwww.tcgplayer.com%2Fsearch%2Fdecks%3FproductLineName%3Dmagic%26q%3DGilder%2BBairn",
    "edhrec": "https://edhrec.com/route/?cc=Gilder+Bairn"
  },
  "purchase_uris": {
    "tcgplayer": "https://partner.tcgplayer.com/c/4931599/1830156/21018?subId1=api&u=https%3A%2F%2Fwww.tcgplayer.com%2Fproduct%2F210407%3Fpage%3D1",
    "cardmarket": "https://www.cardmarket.com/en/Magic/Products?idProduct=443153&referrer=scryfall&utm_campaign=card_prices&utm_medium=text&utm_source=scryfall",
    "cardhoarder": "https://www.cardhoarder.com/cards?affiliate_id=scryfall&data%5Bsearch%5D=Gilder+Bairn&ref=card-profile&utm_campaign=affiliate&utm_medium=card&utm_source=scryfall"
  }
}